tf_vars_to_pydantic/__init__.py
tf_vars_to_pydantic/_typing.py
tf_vars_to_pydantic/convert.py
tf_vars_to_pydantic/exceptions.py
tf_vars_to_pydantic/py.typed
tf_vars_to_pydantic-0.1.2.dist-info/LICENSE
tf_vars_to_pydantic-0.1.2.dist-info/METADATA
tf_vars_to_pydantic-0.1.2.dist-info/WHEEL
tf_vars_to_pydantic-0.1.2.dist-info/RECORD
