Metadata-Version: 2.1
Name: tf-vars-to-pydantic
Version: 0.1.2
Summary: Tf Vars To Pydantic
Home-page: https://github.com/andrewthetechie/tf-vars-to-pydantic
License: MIT
Author: Andrew Herrington
Author-email: andrew.the.techie@gmail.com
Requires-Python: >=3.11,<4.0
Classifier: Development Status :: 4 - Beta
Classifier: License :: OSI Approved :: MIT License
Classifier: Programming Language :: Python :: 3
Classifier: Programming Language :: Python :: 3.11
Classifier: Programming Language :: Python :: 3.12
Requires-Dist: pydantic (>=1.10.0,<2.0.0)
Requires-Dist: python-hcl2 (>=4.3.0,<5.0.0)
Project-URL: Changelog, https://github.com/andrewthetechie/tf-vars-to-pydantic/releases
Project-URL: Documentation, https://tf-vars-to-pydantic.readthedocs.io
Project-URL: Repository, https://github.com/andrewthetechie/tf-vars-to-pydantic
